CHANGES.txt
MANIFEST.in
README.md
requirements.txt
setup.py
GeobricksProj4ToEPSG.egg-info/PKG-INFO
GeobricksProj4ToEPSG.egg-info/SOURCES.txt
GeobricksProj4ToEPSG.egg-info/dependency_links.txt
GeobricksProj4ToEPSG.egg-info/entry_points.txt
GeobricksProj4ToEPSG.egg-info/pbr.json
GeobricksProj4ToEPSG.egg-info/requires.txt
GeobricksProj4ToEPSG.egg-info/top_level.txt
geobricks_proj4_to_epsg/__init__.py
geobricks_proj4_to_epsg/__init__.pyc
geobricks_proj4_to_epsg/cli/__init__.py
geobricks_proj4_to_epsg/cli/cli.py
geobricks_proj4_to_epsg/config/__init__.py
geobricks_proj4_to_epsg/config/config.py
geobricks_proj4_to_epsg/core/__init__.py
geobricks_proj4_to_epsg/core/__init__.pyc
geobricks_proj4_to_epsg/core/proj4_to_epsg.py
geobricks_proj4_to_epsg/core/proj4_to_epsg.pyc
geobricks_proj4_to_epsg/data/epsg.json
geobricks_proj4_to_epsg/data/epsg_original.json
geobricks_proj4_to_epsg/data/pyproj/epsg
geobricks_proj4_to_epsg/rest/__init__.py
geobricks_proj4_to_epsg/rest/proj4_to_epsg_main.py
geobricks_proj4_to_epsg/rest/proj4_to_epsg_rest.py
geobricks_proj4_to_epsg/utils/__init__.py
geobricks_proj4_to_epsg/utils/epsg_json_file.py
geobricks_proj4_to_epsg/utils/pyproj_epsg_to_json.py
geobricks_proj4_to_epsg_test/__init__.py
geobricks_proj4_to_epsg_test/test_suite/__init__.py
geobricks_proj4_to_epsg_test/test_suite/proj4_to_epsg_test.py