Metadata-Version: 1.0
Name: GeobricksProj4ToEPSG
Version: 0.0.15
Summary: Geobricks Proj4 to EPSG code convert library
Home-page: http://pypi.python.org/pypi/GeobricksProj4ToEPSG/
Author: Simone Murzilli; Guido Barbaglia
Author-email: geobrickspy@gmail.com
License: LICENSE.txt
Keywords: geobricks,proj4,epsg,gis,geo
Platform: UNKNOWN
